design.v
// design.v
// A parameterizable synchronous ALU
module alu #(
    parameter DATA_WIDTH = 8
) (
    input  wire                  clk,
    input  wire                  rst_n,
    input  wire                  en,
    input  wire [3:0]            opcode,
    input  wire [DATA_WIDTH-1:0] a,
    input  wire [DATA_WIDTH-1:0] b,
    output reg  [DATA_WIDTH-1:0] result,
    output reg                   carry_out,
    output reg                   zero,
    output reg                   overflow,
    output reg                   negative
);

    // Opcodes
    localparam OP_ADD = 4'b0000;
    localparam OP_SUB = 4'b0001;
    localparam OP_AND = 4'b0010;
    localparam OP_OR  = 4'b0011;
    localparam OP_XOR = 4'b0100;
    localparam OP_NOT = 4'b0101;
    localparam OP_LSL = 4'b0110;
    localparam OP_LSR = 4'b0111;
    localparam OP_ASR = 4'b1000;
    localparam OP_EQ  = 4'b1001;
    localparam OP_GT  = 4'b1010;
    localparam OP_LT  = 4'b1011;

    // Internal registers for combinational ALU output
    reg [DATA_WIDTH-1:0] next_result;
    reg                  next_carry_out;
    reg                  next_zero;
    reg                  next_overflow;
    reg                  next_negative;

    // Combinational Logic
    always @(*) begin
        // Default values
        next_result    = {DATA_WIDTH{1'b0}};
        next_carry_out = 1'b0;
        next_zero      = 1'b0;
        next_overflow  = 1'b0;
        next_negative  = 1'b0;

        if (en) begin
            case (opcode)
                OP_ADD: begin
                    {next_carry_out, next_result} = a + b;
                    // Overflow flag for signed addition: operands have same sign, result has opposite sign
                    next_overflow = (a[DATA_WIDTH-1] == b[DATA_WIDTH-1]) && (next_result[DATA_WIDTH-1] != a[DATA_WIDTH-1]);
                end
                OP_SUB: begin
                    {next_carry_out, next_result} = a - b;
                    // Overflow flag for signed subtraction: operands have opposite sign, result sign matches B's sign
                    next_overflow = (a[DATA_WIDTH-1] != b[DATA_WIDTH-1]) && (next_result[DATA_WIDTH-1] == b[DATA_WIDTH-1]);
                end
                OP_AND: begin
                    next_result = a & b;
                end
                OP_OR: begin
                    next_result = a | b;
                end
                OP_XOR: begin
                    next_result = a ^ b;
                end
                OP_NOT: begin
                    next_result = ~a;
                end
                OP_LSL: begin
                    next_result = a << b[2:0]; // Limit shift range to 0-7 for 8-bit safety
                end
                OP_LSR: begin
                    next_result = a >> b[2:0];
                end
                OP_ASR: begin
                    next_result = $signed(a) >>> b[2:0];
                end
                OP_EQ: begin
                    next_result = (a == b) ? {DATA_WIDTH{1'b1}} : {DATA_WIDTH{1'b0}};
                end
                OP_GT: begin
                    next_result = ($signed(a) > $signed(b)) ? {DATA_WIDTH{1'b1}} : {DATA_WIDTH{1'b0}};
                end
                OP_LT: begin
                    next_result = ($signed(a) < $signed(b)) ? {DATA_WIDTH{1'b1}} : {DATA_WIDTH{1'b0}};
                end
                default: begin
                    next_result = {DATA_WIDTH{1'b0}};
                end
            endcase

            next_zero     = (next_result == {DATA_WIDTH{1'b0}});
            next_negative = next_result[DATA_WIDTH-1];
        end else begin
            // Hold state when enable is low
            next_result    = result;
            next_carry_out = carry_out;
            next_zero      = zero;
            next_overflow  = overflow;
            next_negative  = negative;
        end
    end

    // Sequential Logic
    always @(posedge clk or negedge rst_n) begin
        if (!rst_n) begin
            result    <= {DATA_WIDTH{1'b0}};
            carry_out <= 1'b0;
            zero      <= 1'b0;
            overflow  <= 1'b0;
            negative  <= 1'b0;
        end else begin
            result    <= next_result;
            carry_out <= next_carry_out;
            zero      <= next_zero;
            overflow  <= next_overflow;
            negative  <= next_negative;
        end
    end

    // Dump waveform if COCOTB_SIM is defined
    `ifdef COCOTB_SIM
    initial begin
        $dumpfile("waveform.vcd");
        $dumpvars(0, alu);
    end
    `endif

endmodule

waveform.vcd
$date
	Mon May 25 22:31:25 2026
$end
$version
	Icarus Verilog
$end
$timescale
	1ps
$end
$scope module alu $end
$var wire 8 ! a [7:0] $end
$var wire 8 " b [7:0] $end
$var wire 1 # clk $end
$var wire 1 $ en $end
$var wire 4 % opcode [3:0] $end
$var wire 1 & rst_n $end
$var parameter 32 ' DATA_WIDTH $end
$var parameter 4 ( OP_ADD $end
$var parameter 4 ) OP_AND $end
$var parameter 4 * OP_ASR $end
$var parameter 4 + OP_EQ $end
$var parameter 4 , OP_GT $end
$var parameter 4 - OP_LSL $end
$var parameter 4 . OP_LSR $end
$var parameter 4 / OP_LT $end
$var parameter 4 0 OP_NOT $end
$var parameter 4 1 OP_OR $end
$var parameter 4 2 OP_SUB $end
$var parameter 4 3 OP_XOR $end
$var reg 1 4 carry_out $end
$var reg 1 5 negative $end
$var reg 1 6 next_carry_out $end
$var reg 1 7 next_negative $end
$var reg 1 8 next_overflow $end
$var reg 8 9 next_result [7:0] $end
$var reg 1 : next_zero $end
$var reg 1 ; overflow $end
$var reg 8 < result [7:0] $end
$var reg 1 = zero $end
$upscope $end
$enddefinitions $end
$comment Show the parameter values. $end
$dumpall
b100 3
b1 2
b11 1
b101 0
b1011 /
b111 .
b110 -
b1010 ,
b1001 +
b1000 *
b10 )
b0 (
b1000 '
$end
#0
$dumpvars
0=
b0 <
0;
0:
b11111111 9
08
17
06
05
04
0&
b11 %
1$
1#
b1010101 "
b11111111 !
$end
#1
07
b0 9
b0 "
b0 !
b0 %
0$
#5001
0#
#10001
1#
#15001
0#
#20001
1&
1#
#25001
0#
#30001
1#
#35001
b11110 9
1$
b10100 "
b1010 !
0#
#40001
b11110 9
b11110 <
1#
#45001
b11110 9
0$
b110010 "
b110010 !
0#
#50001
1#
#50002
b0 <
b0 9
b0 "
b0 !
0&
#55002
0#
#60002
1#
#65002
0#
#70002
1&
1#
#75002
0#
#80002
1#
#85002
b1000 9
1$
b11 "
b101 !
0#
#90002
b1000 9
b1000 <
1#
#95002
16
b100 9
b1010 "
b11111010 !
0#
#100002
16
b100 9
14
b100 <
1#
#105002
17
18
06
b10000010 9
b1111000 !
0#
#110002
17
18
b10000010 9
15
1;
04
b10000010 <
1#
#115002
07
08
b110 9
b1 %
b100 "
b1010 !
0#
#120002
b110 9
05
0;
b110 <
1#
#125002
17
16
b11111110 9
b101 "
b11 !
0#
#130002
17
16
b11111110 9
15
14
b11111110 <
1#
#130003
05
04
b0 <
07
06
b0 9
b0 "
b0 !
b0 %
0$
0&
#135003
0#
#140003
1#
#145003
0#
#150003
1&
1#
#155003
0#
#160003
1#
#165003
1:
1$
b10 %
b1010101 "
b10101010 !
0#
#170003
1:
1=
1#
#175003
17
b11111111 9
0:
b11 %
b1111 "
b11110000 !
0#
#180003
17
b11111111 9
15
0=
b11111111 <
1#
#185003
17
b10101010 9
b100 %
b11111111 "
b1010101 !
0#
#190003
17
b10101010 9
b10101010 <
1#
#195003
17
b11111111 9
b101 %
b0 !
0#
#200003
17
b11111111 9
b11111111 <
1#
#200004
05
b0 <
07
b0 9
b0 "
b0 %
0$
0&
#205004
0#
#210004
1#
#215004
0#
#220004
1&
1#
#225004
0#
#230004
1#
#235004
b111000 9
1$
b110 %
b11 "
b111 !
0#
#240004
b111000 9
b111000 <
1#
#245004
b1111 9
b111 %
b100 "
b11110000 !
0#
#250004
b1111 9
b1111 <
1#
#255004
b10000 9
b1000 %
b10 "
b1000000 !
0#
#260004
b10000 9
b10000 <
1#
#265004
17
b11100000 9
b10000000 !
0#
#270004
17
b11100000 9
15
b11100000 <
1#
#270005
05
b0 <
07
b0 9
b0 "
b0 !
b0 %
0$
0&
#275005
0#
#280005
1#
#285005
0#
#290005
1&
1#
#295005
0#
#300005
1#
#305005
17
b11111111 9
1$
b1001 %
b101 "
b101 !
0#
#310005
17
b11111111 9
15
b11111111 <
1#
#315005
1:
07
b0 9
b11 "
0#
#320005
1:
05
1=
b0 <
1#
#325005
17
b11111111 9
0:
b1010 %
b11111110 "
0#
#330005
17
b11111111 9
15
0=
b11111111 <
1#
#335005
17
b11111111 9
b1011 %
b101 "
b11111110 !
0#
#340005
1#
#340006
05
b0 <
07
b0 9
b0 "
b0 !
b0 %
0$
0&
#345006
0#
#350006
1#
#355006
0#
#360006
1&
1#
#365006
0#
#370006
1#
#375006
1:
1$
b1011 %
b1100 "
b111001 !
0#
#380006
1:
1=
1#
#385006
17
b11111101 9
0:
b11 %
b1111101 "
b10001100 !
0#
#390006
17
b11111101 9
15
0=
b11111101 <
1#
#395006
17
b11111111 9
b1010 %
b110100 "
b1000111 !
0#
#400006
17
b11111111 9
b11111111 <
1#
#405006
16
07
b100 9
b0 %
b11011000 "
b101100 !
0#
#410006
16
b100 9
05
14
b100 <
1#
#415006
06
b101111 9
b11 %
b101111 "
b1111 !
0#
#420006
b101111 9
04
b101111 <
1#
#425006
b11 9
b1000 %
b1101 "
b1110111 !
0#
#430006
b11 9
b11 <
1#
#435006
17
b11110111 9
b11 %
b11010110 "
b1100101 !
0#
#440006
17
b11110111 9
15
b11110111 <
1#
#445006
18
16
07
b1110011 9
b0 %
b10001110 "
b11100101 !
0#
#450006
18
16
b1110011 9
05
1;
14
b1110011 <
1#
#455006
17
08
06
b10101110 9
b101 %
b11011000 "
b1010001 !
0#
#460006
17
b10101110 9
15
0;
04
b10101110 <
1#
#465006
17
b11001111 9
b11 %
b1001111 "
b10001110 !
0#
#470006
17
b11001111 9
b11001111 <
1#
#475006
18
07
b1111000 9
b1 %
b110100 "
b10101100 !
0#
#480006
18
b1111000 9
05
1;
b1111000 <
1#
#485006
08
b111101 9
b101 %
b110001 "
b11000010 !
0#
#490006
b111101 9
0;
b111101 <
1#
#495006
18
16
b110111 9
b0 %
b10000111 "
b10110000 !
0#
#500006
18
16
b110111 9
1;
14
b110111 <
1#
#505006
17
08
06
b10000000 9
b110 %
b111111 "
b11101011 !
0#
#510006
17
b10000000 9
15
0;
04
b10000000 <
1#
#515006
17
b11111111 9
b1010 %
b10010110 "
b101000 !
0#
#520006
17
b11111111 9
b11111111 <
1#
#525006
17
b11111111 9
b1011 %
b1100010 "
b10111001 !
0#
#530006
1#
#535006
17
b11111111 9
b1010 %
b10111 "
b100011 !
0#
#540006
1#
#545006
18
16
17
b11100000 9
b1 %
b10010100 "
b1110100 !
0#
#550006
17
18
16
b11100000 9
1;
14
b11100000 <
1#
#555006
17
08
06
b10111000 9
b110 %
b110011 "
b1110111 !
0#
#560006
17
b10111000 9
0;
04
b10111000 <
1#
#565006
1:
07
b0 9
b1010 %
b11101000 "
b10001110 !
0#
#570006
1:
05
1=
b0 <
1#
#575006
b1000101 9
0:
b101 %
b1010011 "
b10111010 !
0#
#580006
b1000101 9
0=
b1000101 <
1#
#585006
1:
b0 9
b1010 %
b1101011 "
b10110101 !
0#
#590006
1:
1=
b0 <
1#
#595006
1:
b1001 %
b100100 "
b10001000 !
0#
#600006
1#
#605006
b1010101 9
0:
b10 %
b1111101 "
b1010111 !
0#
#610006
b1010101 9
0=
b1010101 <
1#
#615006
b101110 9
b100 %
b11000010 "
b11101100 !
0#
#620006
b101110 9
b101110 <
1#
#625006
16
b10110 9
b0 %
b10100110 "
b1110000 !
0#
#630006
16
b10110 9
14
b10110 <
1#
#635006
17
06
b10001010 9
b101 %
b10000 "
b1110101 !
0#
#640006
17
b10001010 9
15
04
b10001010 <
1#
#645006
07
b1000100 9
b1 %
b10001001 "
b11001101 !
0#
#650006
b1000100 9
05
b1000100 <
1#
#655006
17
b11101101 9
b11 %
b10100001 "
b1101100 !
0#
#660006
17
b11101101 9
15
b11101101 <
1#
#665006
17
b11111111 9
b1010 %
b11001010 "
b11111111 !
0#
#670006
17
b11111111 9
b11111111 <
1#
#675006
17
b10100011 9
b100 %
b1001001 "
b11101010 !
0#
#680006
17
b10100011 9
b10100011 <
1#
#685006
17
b11111111 9
b1011 %
b1111110 "
b1000111 !
0#
#690006
17
b11111111 9
b11111111 <
1#
#695006
1:
07
b0 9
b1001 %
b11011011 "
b10000110 !
0#
#700006
1:
05
1=
b0 <
1#
#705006
17
b11111101 9
0:
b11 %
b10111001 "
b11001100 !
0#
#710006
17
b11111101 9
15
0=
b11111101 <
1#
#715006
16
07
b1001010 9
b1 %
b11111100 "
b1000110 !
0#
#720006
16
b1001010 9
05
14
b1001010 <
1#
#725006
06
b11000 9
b10 %
b111000 "
b11000 !
0#
#730006
b11000 9
04
b11000 <
1#
#735006
1:
b0 9
b1001 %
b11011000 "
b1010001 !
0#
#740006
1:
1=
b0 <
1#
#745006
1:
b110 %
b11000101 "
b100000 !
0#
#750006
1#
#755006
17
b11101111 9
0:
b1000 %
b10000000 "
b11101111 !
0#
#760006
17
b11101111 9
15
0=
b11101111 <
1#
#765006
1:
07
b0 9
b1010 %
b111010 "
b101 !
0#
#770006
1:
05
1=
b0 <
1#
#775006
17
16
b11011010 9
0:
b1 %
b10101110 "
b10001000 !
0#
#780006
17
16
b11011010 9
15
0=
14
b11011010 <
1#
#785006
17
06
b10010110 9
b10 %
b11011110 "
b10010110 !
0#
#790006
17
b10010110 9
04
b10010110 <
1#
#795006
17
b11111111 9
b1011 %
b1 "
b11101000 !
0#
#800006
17
b11111111 9
b11111111 <
1#
#805006
17
b11110000 9
b1000 %
b1011011 "
b10000110 !
0#
#810006
17
b11110000 9
b11110000 <
1#
#815006
17
b11111111 9
b1010 %
b10011000 "
b110110 !
0#
#820006
17
b11111111 9
b11111111 <
1#
#825006
17
b10011010 9
b101 %
b1001110 "
b1100101 !
0#
#830006
17
b10011010 9
b10011010 <
1#
#835006
1:
07
b0 9
b1001 %
b0 "
b1010010 !
0#
#840006
1:
05
1=
b0 <
1#
#845006
17
16
b10011111 9
0:
b0 %
b11111010 "
b10100101 !
0#
#850006
17
16
b10011111 9
15
0=
14
b10011111 <
1#
#855006
17
06
b10000000 9
b100 %
b10111001 "
b111001 !
0#
#860006
17
b10000000 9
04
b10000000 <
1#
#865006
07
b1111111 9
b11 %
b11101 "
b1111010 !
0#
#870006
b1111111 9
05
b1111111 <
1#
#875006
17
b11111111 9
b1011 %
b101011 "
b101000 !
0#
#880006
17
b11111111 9
15
b11111111 <
1#
#885006
17
b11111111 9
b1000 %
b100011 "
b11111000 !
0#
#890006
1#
#895006
1:
07
b0 9
b1010 %
b1000001 "
b1000000 !
0#
#900006
1:
05
1=
b0 <
1#
#905006
17
b10100111 9
0:
b100 %
b1010100 "
b11110011 !
0#
#910006
17
b10100111 9
15
0=
b10100111 <
1#
#915006
17
b11111101 9
b1000 %
b1101100 "
b11011000 !
0#
#920006
17
b11111101 9
b11111101 <
1#
#925006
1:
07
b0 9
b110 %
b10011111 "
b1100110 !
0#
#930006
1:
05
1=
b0 <
1#
#935006
17
b10111111 9
0:
b1000 %
b11100000 "
b10111111 !
0#
#940006
17
b10111111 9
15
0=
b10111111 <
1#
#945006
17
b11111111 9
b11 %
b111101 "
b11100111 !
0#
#950006
17
b11111111 9
b11111111 <
1#
#955006
17
b10001100 9
b101 %
b100000 "
b1110011 !
0#
#960006
17
b10001100 9
b10001100 <
1#
#965006
1:
07
b0 9
b1001 %
b1110101 "
b1010 !
0#
#970006
1:
05
1=
b0 <
1#
#975006
b1101101 9
0:
b1 %
b11 "
b1110000 !
0#
#980006
b1101101 9
0=
b1101101 <
1#
#985006
17
16
b10101001 9
b1110101 "
b11110 !
0#
#990006
17
16
b10101001 9
15
14
b10101001 <
1#
#995006
07
16
b1100111 9
b10101001 "
b10000 !
0#
#1000006
16
b1100111 9
05
b1100111 <
1#
#1005006
17
06
b11111111 9
b1010 %
b10001110 "
b1111001 !
0#
#1010006
17
b11111111 9
15
04
b11111111 <
1#
#1015006
17
b11111111 9
b1000 %
b1101101 "
b11111000 !
0#
#1020006
1#
#1025006
17
b11110011 9
b11 %
b11110010 "
b1000011 !
0#
#1030006
17
b11110011 9
b11110011 <
1#
#1035006
17
b11110010 9
b11010000 "
b11110010 !
0#
#1040006
17
b11110010 9
b11110010 <
1#
#1045006
1:
07
b0 9
b1010 %
b110001 "
b110000 !
0#
#1050006
1:
05
1=
b0 <
1#
#1055006
17
b10000000 9
0:
b110 %
b10110101 "
b11011100 !
0#
#1060006
17
b10000000 9
15
0=
b10000000 <
1#
#1065006
17
b11111111 9
b1011 %
b11101111 "
b11010010 !
0#
#1070006
17
b11111111 9
b11111111 <
1#
#1075006
07
b1001101 9
b0 %
b110010 "
b11011 !
0#
#1080006
b1001101 9
05
b1001101 <
1#
#1085006
b100001 9
b1 %
b10101101 "
b11001110 !
0#
#1090006
b100001 9
b100001 <
1#
#1095006
b1111111 9
b11 %
b1100010 "
b1111111 !
0#
#1100006
b1111111 9
b1111111 <
1#
#1105006
17
b10000000 9
b110 %
b1000111 "
b11100101 !
0#
#1110006
17
b10000000 9
15
b10000000 <
1#
#1115006
07
b1 9
b111 %
b10001110 "
b1011101 !
0#
#1120006
b1 9
05
b1 <
1#
#1125006
b1 9
b100110 "
b1111111 !
0#
#1130006
1#
#1135006
17
b11111111 9
b1010 %
b11001 "
b110010 !
0#
#1140006
17
b11111111 9
15
b11111111 <
1#
#1145006
07
b101111 9
b11 %
b101111 "
b111 !
0#
#1150006
b101111 9
05
b101111 <
1#
#1155006
b1010101 9
b111 %
b11010000 "
b1010101 !
0#
#1160006
b1010101 9
b1010101 <
1#
#1165006
17
b11000000 9
b110 %
b1101101 "
b11110110 !
0#
#1170006
17
b11000000 9
15
b11000000 <
1#
#1175006
17
b11100000 9
b1010100 "
b11110 !
0#
#1180006
17
b11100000 9
b11100000 <
1#
#1185006
17
b11000110 9
b100 %
b11000111 "
b1 !
0#
#1190006
17
b11000110 9
b11000110 <
1#
#1195006
17
b10100000 9
b110 %
b10010010 "
b11101000 !
0#
#1200006
17
b10100000 9
b10100000 <
1#
#1205006
17
b11111111 9
b11 %
b1001111 "
b11111001 !
0#
#1210006
17
b11111111 9
b11111111 <
1#
#1215006
16
07
b110 9
b0 %
b1101111 "
b10010111 !
0#
#1220006
16
b110 9
05
14
b110 <
1#
#1225006
17
06
b10111111 9
b10100000 "
b11111 !
0#
#1230006
17
b10111111 9
15
04
b10111111 <
1#
#1235006
07
b1 9
b1000 %
b11110100 "
b11001 !
0#
#1240006
b1 9
05
b1 <
1#
#1245006
b10 9
b11101 "
b1010000 !
0#
#1250006
b10 9
b10 <
1#
#1255006
17
16
b11001010 9
b1 %
b1011111 "
b101001 !
0#
#1260006
17
16
b11001010 9
15
14
b11001010 <
1#
#1265006
07
06
b100010 9
b110 %
b1111000 "
b100010 !
0#
#1270006
b100010 9
05
04
b100010 <
1#
#1275006
1:
b0 9
b1001 %
b1111110 "
b111101 !
0#
#1280006
1:
1=
b0 <
1#
#1285006
b101000 9
0:
b110 %
b101001 "
b10100 !
0#
#1290006
b101000 9
0=
b101000 <
1#
#1295006
17
b10100101 9
b11 %
b10000101 "
b10100001 !
0#
#1300006
17
b10100101 9
15
b10100101 <
1#
#1305006
17
b11011010 9
b100 %
b1111010 "
b10100000 !
0#
#1310006
17
b11011010 9
b11011010 <
1#
#1315006
1:
07
b0 9
b1010 %
b1000011 "
b11001010 !
0#
#1320006
1:
05
1=
b0 <
1#
#1325006
b1100110 9
0:
b101 %
b11101010 "
b10011001 !
0#
#1330006
b1100110 9
0=
b1100110 <
1#
#1335006
b10 9
b111 %
b100 "
b100101 !
0#
#1340006
b10 9
b10 <
1#
#1345006
b1 9
b1000 %
b100101 "
b110011 !
0#
#1350006
b1 9
b1 <
1#
#1355006
b101 9
b10 %
b10000111 "
b1101101 !
0#
#1360006
b101 9
b101 <
1#
#1365006
17
b10110011 9
b11 %
b100011 "
b10110010 !
0#
#1370006
17
b10110011 9
15
b10110011 <
1#
